{
  "annotations": {
    "list": [
      {
        "builtIn": 1,
        "datasource": {
          "type": "grafana",
          "uid": "-- Grafana --"
        },
        "enable": true,
        "hide": true,
        "iconColor": "rgba(0, 211, 255, 1)",
        "name": "Annotations & Alerts",
        "type": "dashboard"
      }
    ]
  },
  "editable": true,
  "fiscalYearStartMonth": 0,
  "graphTooltip": 0,
  "id": 1,
  "links": [],
  "panels": [
    {
      "collapsed": true,
      "gridPos": {
        "h": 1,
        "w": 24,
        "x": 0,
        "y": 0
      },
      "id": 7,
      "panels": [],
      "title": "Sentiment App Graphs",
      "type": "row"
    },
    {
      "datasource": {
        "type": "prometheus",
        "uid": "prometheus"
      },
      "fieldConfig": {
        "defaults": {
          "color": {
            "mode": "thresholds"
          },
          "mappings": [],
          "thresholds": {
            "mode": "absolute",
            "steps": [
              {
                "color": "green"
              },
              {
                "color": "red",
                "value": 80
              }
            ]
          }
        },
        "overrides": []
      },
      "gridPos": {
        "h": 8,
        "w": 12,
        "x": 0,
        "y": 1
      },
      "id": 4,
      "options": {
        "colorMode": "value",
        "graphMode": "area",
        "justifyMode": "auto",
        "orientation": "auto",
        "percentChangeColorMode": "standard",
        "reduceOptions": {
          "calcs": [
            "lastNotNull"
          ],
          "fields": "",
          "values": false
        },
        "showPercentChange": false,
        "textMode": "auto",
        "wideLayout": true
      },
      "pluginVersion": "12.0.0",
      "targets": [
        {
          "disableTextWrap": false,
          "editorMode": "builder",
          "expr": "sentiment_app_requests_total",
          "fullMetaSearch": false,
          "includeNullMetadata": false,
          "legendFormat": "",
          "range": true,
          "refId": "A",
          "useBackend": false
        }
      ],
      "title": "Total review requests",
      "type": "stat"
    },
    {
      "datasource": {
        "type": "prometheus",
        "uid": "prometheus"
      },
      "fieldConfig": {
        "defaults": {
          "color": {
            "mode": "thresholds"
          },
          "mappings": [],
          "thresholds": {
            "mode": "absolute",
            "steps": [
              {
                "color": "green"
              },
              {
                "color": "red",
                "value": 80
              }
            ]
          }
        },
        "overrides": []
      },
      "gridPos": {
        "h": 8,
        "w": 12,
        "x": 12,
        "y": 1
      },
      "id": 3,
      "options": {
        "minVizHeight": 75,
        "minVizWidth": 75,
        "orientation": "auto",
        "reduceOptions": {
          "calcs": [
            "lastNotNull"
          ],
          "fields": "",
          "values": false
        },
        "showThresholdLabels": false,
        "showThresholdMarkers": true,
        "sizing": "auto"
      },
      "pluginVersion": "12.0.0",
      "targets": [
        {
          "disableTextWrap": false,
          "editorMode": "builder",
          "expr": "sentiment_app_review_length",
          "fullMetaSearch": false,
          "includeNullMetadata": true,
          "legendFormat": "__auto",
          "range": true,
          "refId": "A",
          "useBackend": false
        }
      ],
      "title": "Review Length Gauge",
      "type": "gauge"
    },
    {
      "datasource": {
        "type": "prometheus",
        "uid": "prometheus"
      },
      "fieldConfig": {
        "defaults": {
          "color": {
            "mode": "palette-classic"
          },
          "custom": {
            "axisBorderShow": false,
            "axisCenteredZero": false,
            "axisColorMode": "text",
            "axisLabel": "",
            "axisPlacement": "auto",
            "barAlignment": 0,
            "barWidthFactor": 0.6,
            "drawStyle": "line",
            "fillOpacity": 0,
            "gradientMode": "none",
            "hideFrom": {
              "legend": false,
              "tooltip": false,
              "viz": false
            },
            "insertNulls": false,
            "lineInterpolation": "linear",
            "lineWidth": 1,
            "pointSize": 5,
            "scaleDistribution": {
              "type": "linear"
            },
            "showPoints": "auto",
            "spanNulls": false,
            "stacking": {
              "group": "A",
              "mode": "none"
            },
            "thresholdsStyle": {
              "mode": "off"
            }
          },
          "mappings": [],
          "thresholds": {
            "mode": "absolute",
            "steps": [
              {
                "color": "green"
              },
              {
                "color": "red",
                "value": 80
              }
            ]
          }
        },
        "overrides": []
      },
      "gridPos": {
        "h": 8,
        "w": 12,
        "x": 0,
        "y": 9
      },
      "id": 1,
      "options": {
        "legend": {
          "calcs": [],
          "displayMode": "list",
          "placement": "bottom",
          "showLegend": false
        },
        "tooltip": {
          "hideZeros": false,
          "mode": "single",
          "sort": "none"
        }
      },
      "pluginVersion": "12.0.0",
      "targets": [
        {
          "datasource": {
            "type": "prometheus",
            "uid": "prometheus"
          },
          "disableTextWrap": false,
          "editorMode": "builder",
          "expr": "sentiment_app_review_length",
          "fullMetaSearch": false,
          "includeNullMetadata": true,
          "legendFormat": "Review Length",
          "range": true,
          "refId": "A",
          "useBackend": false
        }
      ],
      "title": "Sentiment app review length",
      "type": "timeseries"
    },
    {
      "datasource": {
        "type": "prometheus",
        "uid": "prometheus"
      },
      "fieldConfig": {
        "defaults": {
          "color": {
            "mode": "palette-classic"
          },
          "custom": {
            "axisBorderShow": false,
            "axisCenteredZero": false,
            "axisColorMode": "text",
            "axisLabel": "",
            "axisPlacement": "auto",
            "fillOpacity": 80,
            "gradientMode": "none",
            "hideFrom": {
              "legend": false,
              "tooltip": false,
              "viz": false
            },
            "lineWidth": 1,
            "scaleDistribution": {
              "type": "linear"
            },
            "thresholdsStyle": {
              "mode": "off"
            }
          },
          "mappings": [],
          "thresholds": {
            "mode": "absolute",
            "steps": [
              {
                "color": "green"
              },
              {
                "color": "red",
                "value": 80
              }
            ]
          }
        },
        "overrides": []
      },
      "gridPos": {
        "h": 8,
        "w": 12,
        "x": 12,
        "y": 9
      },
      "id": 8,
      "options": {
        "barRadius": 0,
        "barWidth": 0.97,
        "fullHighlight": false,
        "groupWidth": 0.7,
        "legend": {
          "calcs": [],
          "displayMode": "list",
          "placement": "bottom",
          "showLegend": true
        },
        "orientation": "auto",
        "showValue": "auto",
        "stacking": "none",
        "tooltip": {
          "hideZeros": false,
          "mode": "single",
          "sort": "none"
        },
        "xTickLabelRotation": 0,
        "xTickLabelSpacing": 100
      },
      "pluginVersion": "12.0.0",
      "targets": [
        {
          "disableTextWrap": false,
          "editorMode": "builder",
          "expr": "histogram_quantile(0.95, sum by(le) (rate(sentiment_app_response_time_seconds_bucket[$__rate_interval])))",
          "fullMetaSearch": false,
          "includeNullMetadata": false,
          "legendFormat": "__auto",
          "range": true,
          "refId": "A",
          "useBackend": false
        }
      ],
      "title": "Sentiment App Response Time",
      "type": "barchart"
    },
    {
      "collapsed": false,
      "gridPos": {
        "h": 1,
        "w": 24,
        "x": 0,
        "y": 17
      },
      "id": 6,
      "panels": [],
      "title": "Memory Usage Graphs",
      "type": "row"
    },
    {
      "datasource": {
        "type": "prometheus",
        "uid": "prometheus"
      },
      "fieldConfig": {
        "defaults": {
          "color": {
            "mode": "thresholds"
          },
          "mappings": [],
          "thresholds": {
            "mode": "absolute",
            "steps": [
              {
                "color": "green"
              },
              {
                "color": "red",
                "value": 80
              }
            ]
          }
        },
        "overrides": []
      },
      "gridPos": {
        "h": 8,
        "w": 12,
        "x": 0,
        "y": 18
      },
      "id": 5,
      "options": {
        "minVizHeight": 75,
        "minVizWidth": 75,
        "orientation": "auto",
        "reduceOptions": {
          "calcs": [
            "lastNotNull"
          ],
          "fields": "",
          "values": false
        },
        "showThresholdLabels": false,
        "showThresholdMarkers": true,
        "sizing": "auto"
      },
      "pluginVersion": "12.0.0",
      "targets": [
        {
          "disableTextWrap": false,
          "editorMode": "builder",
          "expr": "container_memory_usage_bytes{container=\"grafana\"}",
          "fullMetaSearch": false,
          "includeNullMetadata": true,
          "legendFormat": "__auto",
          "range": true,
          "refId": "A",
          "useBackend": false
        }
      ],
      "title": "Grafana memory usage",
      "type": "gauge"
    },
    {
      "datasource": {
        "type": "prometheus",
        "uid": "prometheus"
      },
      "fieldConfig": {
        "defaults": {
          "color": {
            "mode": "thresholds"
          },
          "mappings": [],
          "thresholds": {
            "mode": "absolute",
            "steps": [
              {
                "color": "green"
              },
              {
                "color": "red",
                "value": 80
              }
            ]
          }
        },
        "overrides": []
      },
      "gridPos": {
        "h": 8,
        "w": 12,
        "x": 12,
        "y": 18
      },
      "id": 2,
      "options": {
        "minVizHeight": 75,
        "minVizWidth": 75,
        "orientation": "auto",
        "reduceOptions": {
          "calcs": [
            "lastNotNull"
          ],
          "fields": "",
          "values": false
        },
        "showThresholdLabels": false,
        "showThresholdMarkers": true,
        "sizing": "auto"
      },
      "pluginVersion": "12.0.0",
      "targets": [
        {
          "disableTextWrap": false,
          "editorMode": "builder",
          "expr": "container_memory_usage_bytes{container=\"prometheus\"}",
          "fullMetaSearch": false,
          "includeNullMetadata": true,
          "legendFormat": "__auto",
          "range": true,
          "refId": "A",
          "useBackend": false
        }
      ],
      "title": "Prometheus Memory usage",
      "type": "gauge"
    }
  ],
  "preload": false,
  "schemaVersion": 41,
  "tags": [],
  "templating": {
    "list": []
  },
  "time": {
    "from": "2025-05-24T21:24:56.544Z",
    "to": "2025-05-24T23:15:51.840Z"
  },
  "timepicker": {},
  "timezone": "browser",
  "title": "Restaurant Sentiment Dashboard",
  "uid": "4cc1803a-707f-4c9c-b130-6977cbe36e13",
  "version": 1
}